nonebot_plugin_mediawiki/__init__.py
nonebot_plugin_mediawiki/config.py
nonebot_plugin_mediawiki/config_manager.py
nonebot_plugin_mediawiki/constants.py
nonebot_plugin_mediawiki/exception.py
nonebot_plugin_mediawiki/fakemwapi.py
nonebot_plugin_mediawiki/mediawiki/LICENSE
nonebot_plugin_mediawiki/mediawiki/README.md
nonebot_plugin_mediawiki/mediawiki/__init__.py
nonebot_plugin_mediawiki/mediawiki/constants.py
nonebot_plugin_mediawiki/mediawiki/exceptions.py
nonebot_plugin_mediawiki/mediawiki/mediawiki.py
nonebot_plugin_mediawiki/mediawiki/mediawikipage.py
nonebot_plugin_mediawiki/mediawiki/utilities.py
nonebot_plugin_mediawiki/utilities.py
nonebot_plugin_mediawiki/worker.py
nonebot_plugin_mediawiki-1.2.8.dist-info/METADATA
nonebot_plugin_mediawiki-1.2.8.dist-info/WHEEL
nonebot_plugin_mediawiki-1.2.8.dist-info/licenses/LICENSE
nonebot_plugin_mediawiki-1.2.8.dist-info/RECORD
