Metadata-Version: 2.4
Name: nonebot-plugin-mediawiki
Version: 1.2.8
Summary: nonebot2 mediawiki 查询插件
License: AGPL-3.0-or-later
License-File: LICENSE
Author: KoishiMoe
Author-email: 68314080+KoishiMoe@users.noreply.github.com
Requires-Python: >=3.9,<4.0.0
Classifier: License :: OSI Approved :: GNU Affero General Public License v3 or later (AGPLv3+)
Classifier: Programming Language :: Python :: 3
Classifier: Programming Language :: Python :: 3.9
Classifier: Programming Language :: Python :: 3.10
Classifier: Programming Language :: Python :: 3.11
Classifier: Programming Language :: Python :: 3.12
Classifier: Programming Language :: Python :: 3.13
Classifier: Programming Language :: Python :: 3.14
Provides-Extra: shot
Requires-Dist: aiohttp (>=3.10.11,<4.0)
Requires-Dist: beautifulsoup4 (>=4.12.3,<5.0)
Requires-Dist: nonebot-adapter-onebot (>=2.4.4,<3.0)
Requires-Dist: nonebot2 (>=2.3.2,<3.0)
Requires-Dist: playwright (>=1.45.1,<2.0) ; extra == "shot"
Project-URL: Repository, https://github.com/KoishiMoe/nonebot-plugin-mediawiki
